{
	"configurations" : 
	[
		{
			"directories" : 
			[
				{
					"build" : ".",
					"jsonFile" : "directory-.-Debug-f5ebdc15457944623624.json",
					"minimumCMakeVersion" : 
					{
						"string" : "3.28"
					},
					"projectIndex" : 0,
					"source" : ".",
					"targetIndexes" : 
					[
						0,
						1
					]
				}
			],
			"name" : "Debug",
			"projects" : 
			[
				{
					"directoryIndexes" : 
					[
						0
					],
					"name" : "sphere-renderer",
					"targetIndexes" : 
					[
						0,
						1
					]
				}
			],
			"targets" : 
			[
				{
					"directoryIndex" : 0,
					"id" : "copy_directory::@6890427a1f51a3e7e1df",
					"jsonFile" : "target-copy_directory-Debug-b6af7d82f423fa5c6396.json",
					"name" : "copy_directory",
					"projectIndex" : 0
				},
				{
					"directoryIndex" : 0,
					"id" : "sphere-renderer::@6890427a1f51a3e7e1df",
					"jsonFile" : "target-sphere-renderer-Debug-fac0c31ab40dbbef8abb.json",
					"name" : "sphere-renderer",
					"projectIndex" : 0
				}
			]
		}
	],
	"kind" : "codemodel",
	"paths" : 
	{
		"build" : "/home/sam/src/cpp/sphere-renderer/cmake-build-debug",
		"source" : "/home/sam/src/cpp/sphere-renderer"
	},
	"version" : 
	{
		"major" : 2,
		"minor" : 6
	}
}
